DataAdaptor/__init__.py
DataAdaptor/config.py
DataAdaptor/input.py
DataAdaptor/test.py
Data_Adaptor_sourav-0.2.8.dist-info/LICENSE
Data_Adaptor_sourav-0.2.8.dist-info/METADATA
Data_Adaptor_sourav-0.2.8.dist-info/WHEEL
Data_Adaptor_sourav-0.2.8.dist-info/top_level.txt
Data_Adaptor_sourav-0.2.8.dist-info/RECORD
