Metadata-Version: 2.1
Name: Data-Adaptor-sourav
Version: 0.2.8
Summary: Input Adaptor to verify file extension
Home-page: UNKNOWN
Author: Crossml
Author-email: sourav@crossml.com
License: MIT
Keywords: Input-adaptor,Adaptor,DataAdaptor
Platform: UNKNOWN
Requires-Python: >=3
Requires-Dist: boto3
Requires-Dist: requests
